ipams/__init__.py
ipams/__main__.py
ipams/cli.py
ipams/config.py
ipams/logging.py
ipams/netbox.py
ipams/output.py
ipams/phpipam.py
ipams/query.py
ipams-1.3.14.dist-info/LICENSE
ipams-1.3.14.dist-info/METADATA
ipams-1.3.14.dist-info/WHEEL
ipams-1.3.14.dist-info/entry_points.txt
ipams-1.3.14.dist-info/top_level.txt
ipams-1.3.14.dist-info/RECORD
