Metadata-Version: 2.1
Name: ipams
Version: 1.3.14
Summary: Tool to query multiple IPAMs.
Home-page: https://github.com/rwxd/ipams
Author: rwxd
Author-email: rwxd@pm.me
License: MIT
Classifier: Programming Language :: Python :: 3.6
Classifier: Programming Language :: Python :: 3.7
Classifier: Programming Language :: Python :: 3.8
License-File: LICENSE
Requires-Dist: pydantic==2.9.2
Requires-Dist: pynetbox==7.4.0
Requires-Dist: PyYAML==6.0.2
Requires-Dist: requests==2.32.3
Requires-Dist: rich==13.9.3
Requires-Dist: typer==0.12.5
